tptk/__init__.py
tptk/__main__.py
tptk/categorical_preprocessor.py
tptk/cli.py
tptk/numerical_preprocessor.py
tptk/pipeline.py
tptk/text_preprocessor.py
tptk/utils.py
tptk-1.0.4.dist-info/METADATA
tptk-1.0.4.dist-info/WHEEL
tptk-1.0.4.dist-info/top_level.txt
tptk-1.0.4.dist-info/RECORD
