Metadata-Version: 2.4
Name: TPTK
Version: 1.0.4
Summary: A Python package for automating text preprocessing tasks.
Home-page: https://github.com/Gaurav-Jaiswal-1/Text-Preprocessing-Toolkit
Author: Gaurav Jaiswal
Author-email: Gaurav Jaiswal <jaiswalgaurav863@gmail.com>
License: MIT
Keywords: text preprocessing,NLP,text cleaning
Requires-Python: >=3.8
Requires-Dist: nltk>=3.5.0
Requires-Dist: pyspellchecker>=0.7.1
Requires-Dist: pandas>=1.2.0
Dynamic: author
Dynamic: home-page
Dynamic: requires-python
